{
    "component": [
        {
            "ComponentId": 587256,
            "ComponentName": "Box-Content",
            "ComponentAliasName": "box-content",
            "ParentId": null,
            "SiteId": 16964,
            "FormatId": 0,
            "DisableAIContentGeneration": false,
            "IsGlobal": false,
            "DesktopHtml": null,
            "TabletHtml": null,
            "MobileHtml": null,
            "AmpHtml": null,
            "JsonLD": null,
            "Keyword": "component-Box-Content",
            "ResourceTypeID": 0,
            "ComponentTypeId": 1,
            "PageLevel": false,
            "ProfileLevel": false,
            "ClientAccessEnabled": true,
            "SetTimeLimit": false,
            "MaxRecord": 1,
            "IsMultipleProfile": false,
            "ResourceSelectionType": 1,
            "EditButtonText": null,
            "ShowDisplayOrder": true,
            "DisplayOrderText": null,
            "Status": true,
            "IsDeleted": false,
            "CreatedBy": 17696,
            "UpdatedBy": 17696,
            "IsUrlBased": false,
            "ModuleId": 0,
            "RecordText": null,
            "MinRecord": 0,
            "RecordVersion": 0,
            "ScopeId": 1,
            "TemplateMiBlockID": 0,
            "IsLinkedWithTemplateMiBlock": false,
            "TemplateId": 0,
            "TabletTemplateId": 0,
            "MobileTemplateId": 0,
            "AmpTemplateId": 0
        }
    ],
    "componentDefinition": [
        {
            "DefinitionId": 2971653,
            "ComponentId": 587256,
            "PropertyName": "Icon Image",
            "PropertyAliasName": "icon-image",
            "PropertyValue": null,
            "ControlId": 7,
            "DisableAIContentGeneration": false,
            "ShowInGrid": false,
            "IsMandatory": true,
            "ResourceTypeId": 319324,
            "ResourceTypeGroupId": 0,
            "SiteId": 16964,
            "Status": true,
            "CreatedBy": 17696,
            "UpdatedBy": 17696,
            "PropertyMaxLength": 1,
            "RegularExpression": null,
            "RegExErrorMessage": null,
            "IsDeleted": false,
            "Tooltip": null,
            "IsIdentifier": false,
            "IsUsedInUrl": false,
            "DisplayOrder": 4,
            "DefinitionTabId": 0,
            "IsClientEdit": false
        },
        {
            "DefinitionId": 2971654,
            "ComponentId": 587256,
            "PropertyName": "ALT Text",
            "PropertyAliasName": "alt-text",
            "PropertyValue": null,
            "ControlId": 1,
            "DisableAIContentGeneration": false,
            "ShowInGrid": false,
            "IsMandatory": false,
            "ResourceTypeId": 0,
            "ResourceTypeGroupId": 0,
            "SiteId": 16964,
            "Status": true,
            "CreatedBy": 17696,
            "UpdatedBy": 17696,
            "PropertyMaxLength": 300,
            "RegularExpression": null,
            "RegExErrorMessage": null,
            "IsDeleted": false,
            "Tooltip": null,
            "IsIdentifier": false,
            "IsUsedInUrl": false,
            "DisplayOrder": 5,
            "DefinitionTabId": 0,
            "IsClientEdit": false
        },
        {
            "DefinitionId": 2971655,
            "ComponentId": 587256,
            "PropertyName": "Text",
            "PropertyAliasName": "text",
            "PropertyValue": null,
            "ControlId": 9,
            "DisableAIContentGeneration": false,
            "ShowInGrid": false,
            "IsMandatory": true,
            "ResourceTypeId": 0,
            "ResourceTypeGroupId": 0,
            "SiteId": 16964,
            "Status": true,
            "CreatedBy": 17696,
            "UpdatedBy": 0,
            "PropertyMaxLength": 500,
            "RegularExpression": null,
            "RegExErrorMessage": null,
            "IsDeleted": false,
            "Tooltip": null,
            "IsIdentifier": false,
            "IsUsedInUrl": false,
            "DisplayOrder": 3,
            "DefinitionTabId": 0,
            "IsClientEdit": false
        },
        {
            "DefinitionId": 2971656,
            "ComponentId": 587256,
            "PropertyName": "Background Image",
            "PropertyAliasName": "background-image",
            "PropertyValue": null,
            "ControlId": 7,
            "DisableAIContentGeneration": false,
            "ShowInGrid": false,
            "IsMandatory": false,
            "ResourceTypeId": 319328,
            "ResourceTypeGroupId": 0,
            "SiteId": 16964,
            "Status": true,
            "CreatedBy": 17696,
            "UpdatedBy": 0,
            "PropertyMaxLength": 1,
            "RegularExpression": null,
            "RegExErrorMessage": null,
            "IsDeleted": false,
            "Tooltip": null,
            "IsIdentifier": false,
            "IsUsedInUrl": false,
            "DisplayOrder": 1,
            "DefinitionTabId": 0,
            "IsClientEdit": false
        },
        {
            "DefinitionId": 2971657,
            "ComponentId": 587256,
            "PropertyName": "Title",
            "PropertyAliasName": "title",
            "PropertyValue": null,
            "ControlId": 1,
            "DisableAIContentGeneration": false,
            "ShowInGrid": true,
            "IsMandatory": true,
            "ResourceTypeId": 0,
            "ResourceTypeGroupId": 0,
            "SiteId": 16964,
            "Status": true,
            "CreatedBy": 17696,
            "UpdatedBy": 17696,
            "PropertyMaxLength": 200,
            "RegularExpression": null,
            "RegExErrorMessage": null,
            "IsDeleted": false,
            "Tooltip": null,
            "IsIdentifier": true,
            "IsUsedInUrl": false,
            "DisplayOrder": 2,
            "DefinitionTabId": 0,
            "IsClientEdit": false
        }
    ],
    "SiteDetail": [
        {
            "SiteId": 16964,
            "SiteName": "Hotel Nikko San Francisco 2025",
            "SiteUrl": "https://hotelnikkosf-automation.w021cms.milestoneinternet.info/",
            "SiteDetails": null,
            "SiteLastModified": "2026-01-19T11:22:24.763",
            "SiteCssLastModified": "2026-01-08T10:43:04.037",
            "SitejsLastModified": "2026-01-08T10:43:04.037",
            "SiteResourceLastModified": "2026-01-08T10:43:04.037",
            "IsDamEnabled": false,
            "ParentSiteId": 0,
            "MidguardProfileId": 0,
            "DamProfileRootFolderId": 0,
            "DamProfileRootFolder": null,
            "LocationId": "",
            "CloudflareZoneId": null,
            "CDNType": null,
            "CpCode": null,
            "SiteStudioTemplateAlias": "",
            "IsDefaultProfile": false,
            "SiteCreatedBy": 0,
            "SiteUpdatedBy": 17671
        }
    ]
}